pdc_dp_means/release.py
pdc_dp_means/__init__.py
pdc_dp_means/dpmeans.py
pdc_dp_means/dp_means_cython.cpython-312-darwin.so
sklearn/conftest.py
sklearn/multiclass.py
sklearn/kernel_approximation.py
sklearn/random_projection.py
sklearn/isotonic.py
sklearn/multioutput.py
sklearn/__init__.py
sklearn/kernel_ridge.py
sklearn/_distributor_init.py
sklearn/_min_dependencies.py
sklearn/naive_bayes.py
sklearn/pipeline.py
sklearn/discriminant_analysis.py
sklearn/exceptions.py
sklearn/_config.py
sklearn/dummy.py
sklearn/base.py
sklearn/calibration.py
sklearn/tree/__init__.py
sklearn/tree/_export.py
sklearn/tree/_reingold_tilford.py
sklearn/tree/_classes.py
sklearn/tree/tests/test_tree.py
sklearn/tree/tests/test_reingold_tilford.py
sklearn/tree/tests/__init__.py
sklearn/tree/tests/test_export.py
sklearn/metrics/_scorer.py
sklearn/metrics/_classification.py
sklearn/metrics/_base.py
sklearn/metrics/_regression.py
sklearn/metrics/__init__.py
sklearn/metrics/pairwise.py
sklearn/metrics/_ranking.py
sklearn/metrics/cluster/_bicluster.py
sklearn/metrics/cluster/__init__.py
sklearn/metrics/cluster/_unsupervised.py
sklearn/metrics/cluster/_supervised.py
sklearn/metrics/cluster/tests/test_supervised.py
sklearn/metrics/cluster/tests/test_common.py
sklearn/metrics/cluster/tests/__init__.py
sklearn/metrics/cluster/tests/test_bicluster.py
sklearn/metrics/cluster/tests/test_unsupervised.py
sklearn/metrics/_plot/regression.py
sklearn/metrics/_plot/det_curve.py
sklearn/metrics/_plot/precision_recall_curve.py
sklearn/metrics/_plot/__init__.py
sklearn/metrics/_plot/roc_curve.py
sklearn/metrics/_plot/confusion_matrix.py
sklearn/metrics/_plot/base.py
sklearn/metrics/_plot/tests/test_precision_recall_display.py
sklearn/metrics/_plot/tests/test_det_curve_display.py
sklearn/metrics/_plot/tests/__init__.py
sklearn/metrics/_plot/tests/test_common_curve_display.py
sklearn/metrics/_plot/tests/test_confusion_matrix_display.py
pdc_dp_means-0.0.8.dist-info/RECORD
pdc_dp_means-0.0.8.dist-info/LICENSE
pdc_dp_means-0.0.8.dist-info/WHEEL
pdc_dp_means-0.0.8.dist-info/top_level.txt
pdc_dp_means-0.0.8.dist-info/METADATA
