Metadata-Version: 2.1
Name: pdc-dp-means
Version: 0.0.8
Author: Or Dinari
Author-email: dinari.or@gmail.com
License: BSD3
Project-URL: Source, https://github.com/BGU-CS-VIL/pdc-dp-means
Project-URL: Tracker, https://github.com/BGU-CS-VIL/pdc-dp-means
Project-URL: Documentation, https://pdc-dp-means.readthedocs.io/en/latest/
Keywords: dp-means clustering
Classifier: Development Status :: 4 - Beta
Classifier: License :: OSI Approved :: BSD License
Classifier: Programming Language :: Python :: 3.8
Classifier: Programming Language :: Python :: 3.9
Classifier: Programming Language :: Python :: 3.10
Classifier: Programming Language :: Python :: 3.11
License-File: LICENSE
Requires-Dist: scikit-learn <1.3,>=1.2
Requires-Dist: numpy <2.0,>=1.23.0
